dash_component_editor.py
dash_component_editor-0.0.8.dist-info/LICENSE.txt
dash_component_editor-0.0.8.dist-info/METADATA
dash_component_editor-0.0.8.dist-info/WHEEL
dash_component_editor-0.0.8.dist-info/top_level.txt
dash_component_editor-0.0.8.dist-info/RECORD
