Metadata-Version: 2.1
Name: dash-component-editor
Version: 0.0.8
Summary: UNKNOWN
Home-page: UNKNOWN
Author: Zhuowen (Kevin) Zhao, Ronald Pandolfi
Author-email: zwenzhao11@gmail.com
License: UNKNOWN
Project-URL: Source, https://github.com/mlexchange/mlex_dash_component_editor.git
Platform: UNKNOWN
Classifier: Environment :: Web Environment
Classifier: Framework :: Dash
Classifier: Operating System :: OS Independent
Classifier: Programming Language :: Python :: 3
Classifier: Topic :: Software Development :: Libraries :: Python Modules
Requires-Python: >=3.0
License-File: LICENSE.txt
Requires-Dist: dash (>=2.9.0)
Requires-Dist: dash-bootstrap-components (>=1.0.0)
Requires-Dist: dash-daq (>=0.1.0)
